python_sixel_windows/__about__.py
python_sixel_windows/__init__.py
python_sixel_windows/cellsize.py
python_sixel_windows/converter.py
python_sixel_windows/python-sixel-windows.py
python_sixel_windows-0.2.1.dist-info/METADATA
python_sixel_windows-0.2.1.dist-info/WHEEL
python_sixel_windows-0.2.1.dist-info/entry_points.txt
python_sixel_windows-0.2.1.dist-info/licenses/LICENSE
python_sixel_windows-0.2.1.dist-info/RECORD
