Metadata-Version: 2.4
Name: python_sixel_windows
Version: 0.2.1
Summary: Display images in the terminal
Project-URL: Homepage, https://github.com/jakekyee/python_sixel_windows
Project-URL: Bug Tracker, https://github.com/jakekyee/python_sixel_windows/issues
License-Expression: GPL-3.0-or-later
License-File: LICENSE
Keywords: image,sixel,terminal
Classifier: Development Status :: 4 - Beta
Classifier: Environment :: Console
Classifier: Intended Audience :: End Users/Desktop
Classifier: License :: OSI Approved :: GNU General Public License (GPL)
Classifier: Operating System :: OS Independent
Classifier: Programming Language :: Python :: 3
Classifier: Topic :: Terminals
Requires-Python: >=3.0
Requires-Dist: pillow
